{
  "notes": [
    {
      "noteText": "I Love TO Post Notes",
      "date": "Sept 2",
      "suspect": "Tom Cat",
      "id": 1
    },
    {
      "noteText": "The pink note card is the most vibrant.",
      "date": "Sept 3",
      "suspect": "Jerry Mouse",
      "id": 2
    },
    {
      "noteText": "This is a note for success.",
      "suspect": "Madelyn Lebsack",
      "date": 1599150550072,
      "id": 3
    },
    {
      "noteText": "sdf",
      "suspect": "Nathanael Champlin",
      "date": 1599151310372,
      "id": 4
    },
    {
      "noteText": "sdfsdf",
      "suspect": "Michel Stamm",
      "date": 1599151325672,
      "id": 5
    },
    {
      "noteText": "aaaaaa",
      "suspect": "Nathanael Champlin",
      "date": 1599151343121,
      "id": 6
    },
    {
      "noteText": "dsf",
      "suspect": "Madelyn Lebsack",
      "date": 1599159557023,
      "id": 7
    },
    {
      "noteText": "a lovey note for the day",
      "suspect": "Madelyn Lebsack",
      "date": 1599161555529,
      "id": 8
    },
    {
      "noteText": "la lal lal",
      "suspect": "Madelyn Lebsack",
      "date": 1599162029344,
      "id": 9
    },
    {
      "noteText": "ssssss",
      "suspect": "Madelyn Lebsack",
      "date": 1599162081333,
      "id": 10
    },
    {
      "noteText": "aaaaa",
      "suspect": "Madelyn Lebsack",
      "date": 1599162130315,
      "id": 11
    },
    {
      "noteText": "bbbb",
      "suspect": "Rogelio Hills",
      "date": 1599162293118,
      "id": 12
    },
    {
      "noteText": "ccc",
      "suspect": "Madelyn Lebsack",
      "date": 1599162378507,
      "id": 13
    },
    {
      "noteText": "dddd",
      "suspect": "Madelyn Lebsack",
      "date": 1599162526222,
      "id": 14
    }
  ]
}